Workbook

Sheet DCF
C2: 2019 | D2: 2020 | E2: 2021 | F2: 2022 | G2: 2023 | H2: 2024E | I2: 2025E | J2: 2026E | K2: 2027E | L2: 2028E | M2: Terminal Year
B3: Revenue | C3: 10187 | D3: 14852 | E3: 16226 | F3: 17536 | G3: 18915 | H3: =$G$3*(1+$N$3)^1 -> 21407.125 | I3: =$G$3*(1+$N$3)^2 -> 24227.598 | J3: =$G$3*(1+$N$3)^3 -> 27419.679 | K3: =$G$3*(1+$N$3)^4 -> 31032.329 | L3: =$G$3*(1+$N$3)^5 -> 35120.961 | N3: =(G3/C3)^(1/5)-1 -> 0.13175392
D4: =(D3-C3)/C3 -> 0.45793659 | E4: =(E3-D3)/D3 -> 0.092512793 | F4: =(F3-E3)/E3 -> 0.080734623 | G4: =(G3-F3)/F3 -> 0.07863823 | H4: =(H3-G3)/H3 -> 0.1164157 | I4: =(I3-H3)/I3 -> 0.1164157 | J4: =(J3-I3)/J3 -> 0.1164157 | K4: =(K3-J3)/K3 -> 0.1164157 | L4: =(L3-K3)/L3 -> 0.1164157
B5: COGS | C5: 5261 | D5: 7812 | E5: 8128 | F5: 7992 | G5: 7670 | H5: =$N$5 -> 7372.6 | I5: =$N$5 -> 7372.6 | J5: =$N$5 -> 7372.6 | K5: =$N$5 -> 7372.6 | L5: =$N$5 -> 7372.6 | N5: =AVERAGE($C$5:$G$5) -> 7372.6
C6: =C5/C3 -> 0.51644252 | D6: =D5/D3 -> 0.52598977 | E6: =E5/E3 -> 0.50092444 | F6: =F5/F3 -> 0.45574818 | G6: =G5/G3 -> 0.40549828 | H6: =H5/H3 -> 0.34439935 | I6: =I5/I3 -> 0.30430586 | J6: =J5/J3 -> 0.26887988 | ... L6: =L5/L3 -> 0.20992023
B7: Gross Income | C7: =C3-C5 -> 4926 | D7: =D3-D5 -> 7040 | E7: =E3-E5 -> 8098 | F7: =F3-F5 -> 9544 | G7: =G3-G5 -> 11245 | H7: =H3-H5 -> 14034.525 | I7: =I3-I5 -> 16854.998 | J7: =J3-J5 -> 20047.079 | ... L7: =L3-L5 -> 27748.361
C8: =C7/C3 -> 0.48355748 | D8: =D7/D3 -> 0.47401023 | E8: =E7/E3 -> 0.49907556 | F8: =F7/F3 -> 0.54425182 | G8: =G7/G3 -> 0.59450172 | H8: =H7/H3 -> 0.65560065 | I8: =I7/I3 -> 0.69569414 | J8: =J7/J3 -> 0.73112012 | ... L8: =L7/L3 -> 0.79007977
B9: SG&A | C9: 3284 | D9: 5528 | E9: 5795 | F9: 6045 | G9: 6576 | H9: =H7*H10 -> 9503.2774 | I9: =I7*I10 -> 11413.12 | J9: =J7*J10 -> 13574.592 | K9: =K7*K10 -> 16020.846 | L9: =L7*L10 -> 18789.404
C10: =C9/C7 -> 0.66666667 | D10: =D9/D7 -> 0.78522727 | E10: =E9/E7 -> 0.71560879 | F10: =F9/F7 -> 0.63338223 | G10: =G9/G7 -> 0.58479324 | H10: =$N$10 -> 0.67713564 | I10: =$N$10 -> 0.67713564 | J10: =$N$10 -> 0.67713564 | K10: =$N$10 -> 0.67713564 | L10: =$N$10 -> 0.67713564 | N10: =AVERAGE($C$10:$G$10) -> 0.67713564
B11: Other | C11: -89 | D11: -434 | E11: -213 | F11: -187 | H11: =$N$11 -> -230.75 | I11: =$N$11 -> -230.75 | J11: =$N$11 -> -230.75 | K11: =$N$11 -> -230.75 | L11: =$N$11 -> -230.75 | N11: =AVERAGE($C$11:$G$11) -> -230.75
B13: EBIT | C13: =C7-C9-C11 -> 1731 | D13: =D7-D9-D11 -> 1946 | E13: =E7-E9-E11 -> 2516 | F13: =F7-F9-F11 -> 3686 | G13: =G7-G9-G11 -> 4669 | H13: =H7-H9-H11 -> 4761.9981 | I13: =I7-I9-I11 -> 5672.6282 | J13: =J7-J9-J11 -> 6703.2374 | ... L13: =L7-L9-L11 -> 9189.7067
C14: =C13/C3 -> 0.16992245 | D14: =D13/D3 -> 0.13102612 | E14: =E13/E3 -> 0.15505978 | F14: =F13/F3 -> 0.21019617 | G14: =G13/G3 -> 0.24684113 | H14: =H13/H3 -> 0.22244921 | I14: =I13/I3 -> 0.23413911 | J14: =J13/J3 -> 0.24446812 | ... L14: =L13/L3 -> 0.26165875
B15: D&A | C15: 1778 | D15: 3257 | E15: 3258 | F15: 3212 | G15: 3162 | H15: =$N$15 -> 2933.4 | I15: =$N$15 -> 2933.4 | J15: =$N$15 -> 2933.4 | K15: =$N$15 -> 2933.4 | L15: =$N$15 -> 2933.4 | N15: =AVERAGE(C15:G15) -> 2933.4
B17: DNWC | C17: 173 | D17: 511 | E17: -7 | F17: -737 | G17: 1105 | H17: =$N$17 -> 173 | I17: =$N$17 -> 173 | J17: =$N$17 -> 173 | K17: =$N$17 -> 173 | L17: =$N$17 -> 173 | N17: =MEDIAN(C17:G17) -> 173
B19: CapEx | C19: 1154 | D19: 1233 | E19: 1160 | F19: 900 | G19: 721 | H19: =$G$19*(1+$N$19)^1 -> 656.26789 | I19: =$G$19*(1+$N$19)^2 -> 597.3475 | J19: =$G$19*(1+$N$19)^3 -> 543.71703 | K19: =$G$19*(1+$N$19)^4 -> 494.90157 | L19: =$G$19*(1+$N$19)^5 -> 450.4688 | N19: =(G19/C19)^(1/5)-1 -> -0.089781012
B21: UFCF | C21: =C13+C15-C17-C19 -> 2182 | D21: =D13+D15-D17-D19 -> 3459 | E21: =E13+E15-E17-E19 -> 4621 | F21: =F13+F15-F17-F19 -> 6735 | G21: =G13+G15-G17-G19 -> 6005 | H21: =H13+H15-H17-H19 -> 6866.1302 | I21: =I13+I15-I17-I19 -> 7835.6807 | J21: =J13+J15-J17-J19 -> 8919.9203 | ... L21: =L13+L15-L17-L19 -> 11499.638
B22: EBITDA | M22: =L13+L15 -> 12123.107
B23: DCF | C23: =C21*(1+WACC!$K$29)^4 -> 2835.3947 | D23: =D21*(1+WACC!$K$29)^3 -> 4209.8793 | E23: =E21*(1+WACC!$K$29)^2 -> 5267.6312 | F23: =F21*(1+WACC!$K$29)^1 -> 7190.8014 | G23: =G21 -> 6005 | H23: =H21/(1+WACC!$K$29)^1 -> 6430.9086 | I23: =I21/(1+WACC!$K$29)^2 -> 6873.8071 | J23: =J21/(1+WACC!$K$29)^3 -> 7328.9522 | K23: =K21/(1+WACC!$K$29)^4 -> 7799.5693 | L23: =L21/(1+WACC!$K$29)^5 -> 8288.686
B25: EV | C25: =SUM(C23:L23)+'TGR & TV'!C32 -> 214349.38
B26: Debt | C26: =WACC!C5 -> 25285
B27: C&Ces | C27: 2960
B29: Equity Value | C29: =C25-C26+C27 -> 192024.38
B30: Shares Outstanding | C30: 534.9
B31: Implied SP | C31: =C29/C30 -> 358.99117

Sheet TGR & TV
B2: Deviation
B3: FCF GR | C3: 0.04
B4: GDP GR | C4: 0.028
B5: Deviation | C5: =C3-C4 -> 0.012
B7: TGR
B8: GDP GR | C8: =C4 -> 0.028
B9: Deviation | C9: =C5 -> 0.012
B10: TGR | C10: =C8-C9 -> 0.016
B12: TV
B13: Terminal UFCF | C13: =DCF!L21 -> 11499.638
B14: TGR | C14: =C10 -> 0.016
B15: WACC | C15: =WACC!K29 -> 0.067676529
B16: TV | C16: =(C13*(1+C14)/(C15-C14)) -> 226091.66
B18: Terminal Multipule
B19: EV/EBITA 1 | C19: 30.011904
B20: EV/EBITA 2 | C20: 19.299098
B21: EV/EBITA 3 | C21: 16.16783
B22: EV/EBITA 4 | C22: 12.804294
B23: EV/EBITA 5 | C23: 13.258548
B24: Avg Multipul | C24: =MEDIAN(C19:C23) -> 16.16783
B26: TV
B27: TEBITDA | C27: =DCF!M22 -> 12123.107
B28: Avg EV/EBITDA | C28: =C24 -> 16.16783
B29: TV | C29: =C27*C28 -> 196004.33
B31: Average TV | C31: =AVERAGE(C29,C16) -> 211047.99
B32: DTV | C32: =C31/((1+WACC!$K$29)^5) -> 152118.75

Sheet WACC
B2: Capital Structure | E2: Cost of Equity | J2: Beta
B3: Total Equity | C3: 119871 | E3: Risk Free Rate | F3: 0.04306 | J3: Beta (5y Monthly) | K3: 0.91
E4: Beta | F4: =K11 -> 0.78452944
B5: Total Debt | C5: 25285 | E5: Market Risk Premium | F5: 0.0404 | J5: Tax | K5: 0.2418
E6: Cost of Equity | F6: =F3+(F4*F5) -> 0.074754989
B7: Total | C7: =SUM(C5,C3) -> 145156 | J7: Debt | K7: =$C$5 -> 25285
B9: % Equity | C9: =C3/C7 -> 0.8258081 | J9: Equity | K9: =$C$3 -> 119871
E10: Cost of Debt
B11: % Debt | C11: =C5/C7 -> 0.1741919 | J11: Unlevered Beta | K11: =(K3)/(1+(1-K5)*(K7/K9)) -> 0.78452944
J18: WACC
J19: Equity
J20: % of Equity | K20: =$C$9 -> 0.8258081
J21: Cost of Equity | K21: =$F$6 -> 0.074754989
J23: Debt
J24: % of Debt | K24: =$C$11 -> 0.1741919
J25: Cost of Debt | K25: 0.045
J27: Tax Rate | K27: =K5 -> 0.2418
J29: WACC | K29: =(K20*K21)+(K24*K25*(1-K27)) -> 0.067676529
